Open_STS_Miner/__init__.py
Open_STS_Miner/sts_miner.py
Open_STS_Miner/sts_predictor.py
Open_STS_Miner/test.py
Open_STS_Miner/util.py
open_sts_miner-0.2.dist-info/METADATA
open_sts_miner-0.2.dist-info/WHEEL
open_sts_miner-0.2.dist-info/licenses/LICENSE
open_sts_miner-0.2.dist-info/RECORD
