Metadata-Version: 2.3
Name: Open_STS_Miner
Version: 0.2
Summary: A package implementing the Spatiotemporal Sequence Miner (STS Miner) algorithm
Project-URL: Homepage, https://github.com/MichaelBiancardi/OpenSTSMiner
Author-email: Michael Biancardi <MichaelBiancardi@my.unt.edu>
License-File: LICENSE
Classifier: License :: OSI Approved :: MIT License
Classifier: Operating System :: OS Independent
Classifier: Programming Language :: Python :: 3
Requires-Python: >=3.8
Requires-Dist: geopandas
Requires-Dist: numpy
Requires-Dist: pandas
